{
  "schemaVersion": 1,
  "id": "carpet-tctc-addition",
  "version": "${mod_version}",
  "name": "Carpet TCTC Addition",
  "description": "A fabric-carpet extension mod. It offers some interesting features.",
  "authors": [
    {
      "name": "The Cat Town Craft",
      "contact": {
        "homepage": "https://github.com/The-Cat-Town-Craft"
      }
    }
  ],
  "contributors": [
    {
      "name": "Hendrix-Shen",
      "contact": {
        "homepage": "https://github.com/Hendrix-Shen"
      }
    }
  ],
  "contact": {
    "homepage": "https://github.com/The-Cat-Town-Craft",
    "issues": "https://github.com/The-Cat-Town-Craft/Carpet-TCTC-Addition/issues",
    "sources": "https://github.com/The-Cat-Town-Craft/Carpet-TCTC-Addition"
  },
  "license": "GPL-v3",
  "icon": "assets/carpet-tctc-addition/icon.png",
  "environment": "*",
  "entrypoints": {
    "main": [
      "top.catowncraft.CarpetTCTCAddition.CarpetTCTCAddition"
    ]
  },
  "mixins": [
    "carpet-tctc-addition.mixins.json"
  ],
  "accessWidener": "carpet-tctc-addition.accesswidener",
  "depends": {
    "carpet": ">=1.4.44",
    "fabricloader": ">=0.9.0",
    "fabric": ">=0.40.1",
    "minecraft": "1.16.5"
  },
  "custom": {
    "modmenu": {
      "parent": "carpet"
    }
  }
}
